dropbox_api_team_6/__init__.py
dropbox_api_team_6/simple_requests.py
dropbox_api_team_6-0.1.0.dist-info/entry_points.txt
dropbox_api_team_6-0.1.0.dist-info/WHEEL
dropbox_api_team_6-0.1.0.dist-info/METADATA
dropbox_api_team_6-0.1.0.dist-info/RECORD
