Metadata-Version: 2.1
Name: dropbox-api-team-6
Version: 0.1.0
Summary: 
Author: sergey_shorin
Author-email: Sergio.shorin@mail.ru
Requires-Python: >=3.8,<4.0
Classifier: Programming Language :: Python :: 3
Classifier: Programming Language :: Python :: 3.8
Classifier: Programming Language :: Python :: 3.9
Requires-Dist: click (>=7.1.2,<8.0.0)
Requires-Dist: dropbox (>=11.7.0,<12.0.0)
Requires-Dist: pytest-mock (>=3.6.0,<4.0.0)
Requires-Dist: requests (>=2.25.1,<3.0.0)
